surrealdb/__init__.py
surrealdb/__version__.py
surrealdb/async_surrealdb.py
surrealdb/error.py
surrealdb/reference.py
surrealdb/surrealdb.py
unofficial_surreal_database-0.2.0.dist-info/METADATA
unofficial_surreal_database-0.2.0.dist-info/WHEEL
unofficial_surreal_database-0.2.0.dist-info/top_level.txt
unofficial_surreal_database-0.2.0.dist-info/RECORD
