Metadata-Version: 2.1
Name: unofficial-surreal-database
Version: 0.2.0
Summary: Client library to query SurrealDB databases.
Home-page: https://github.com/mr-strawberry66/surrealdb-python
Author: Sam Kenney
Author-email: sam.kenney@me.com
License: UNKNOWN
Platform: UNKNOWN
Requires-Dist: httpx (>=0.23.0)
